gradio_neomultimodaltextbox/__init__.py
gradio_neomultimodaltextbox/neomultimodaltextbox.py
gradio_neomultimodaltextbox/neomultimodaltextbox.pyi
gradio_neomultimodaltextbox/rtmt.py
gradio_neomultimodaltextbox/stream_utils.py
gradio_neomultimodaltextbox/templates/component/index.js
gradio_neomultimodaltextbox/templates/component/style.css
gradio_neomultimodaltextbox/templates/example/index.js
gradio_neomultimodaltextbox/templates/example/style.css
gradio_neomultimodaltextbox/templates/example/assets/worker-lPYB70QI.js
gradio_neomultimodaltextbox-0.0.24.dist-info/METADATA
gradio_neomultimodaltextbox-0.0.24.dist-info/WHEEL
gradio_neomultimodaltextbox-0.0.24.dist-info/RECORD
