Metadata-Version: 2.4
Name: gradio_neomultimodaltextbox
Version: 0.0.24
Summary: Python library for Gradio custom component MultimodalTextbox
Author-email: ngaudemet <nicolaenji@yahoo.com>, maoudotte <marc.antoine.oudotte@gmail.com>
License-Expression: Apache-2.0
Keywords: gradio-custom-component,gradio-template-MultimodalTextbox
Classifier: Development Status :: 3 - Alpha
Classifier: Operating System :: OS Independent
Classifier: Programming Language :: Python :: 3
Classifier: Programming Language :: Python :: 3 :: Only
Classifier: Programming Language :: Python :: 3.8
Classifier: Programming Language :: Python :: 3.9
Classifier: Programming Language :: Python :: 3.10
Classifier: Programming Language :: Python :: 3.11
Classifier: Topic :: Scientific/Engineering
Classifier: Topic :: Scientific/Engineering :: Artificial Intelligence
Classifier: Topic :: Scientific/Engineering :: Visualization
Requires-Python: >=3.8
Requires-Dist: gradio>=4.0
Provides-Extra: dev
Requires-Dist: build; extra == 'dev'
Requires-Dist: twine; extra == 'dev'
